jeeves/__init__.py
jeeves/cli.py
jeeves/example.py
jeeves/py.typed
python_jeeves-0.0.1.dist-info/entry_points.txt
python_jeeves-0.0.1.dist-info/LICENSE
python_jeeves-0.0.1.dist-info/WHEEL
python_jeeves-0.0.1.dist-info/METADATA
python_jeeves-0.0.1.dist-info/RECORD
